{
  "settings": {
    "width": 1280, "height": 720, "fps": 30, "font_size": 14,
    "theme": "dracula", "output": "videos/01-skills.mp4",
    "shell_command": "DBUS_SESSION_BUS_ADDRESS=unix:path=/run/user/1000/bus agy --dangerously-skip-permissions",
    "startup_delay": 8,
    "subtitle_style": "FontName=Sans,FontSize=16,PrimaryColour=&H00FFFFFF,OutlineColour=&H40000000,BackColour=&H40000000,Outline=1,Shadow=1,BorderStyle=4,MarginV=20,MarginL=40,MarginR=40"
  },
  "actions": [
    {"at": 0.0,  "type": "subtitle", "text": "AGY CLI  ·  Demo 1: Built-in Skills"},
    {"at": 4.0,  "type": "subtitle", "text": "Type /skills to browse all available skills"},
    {"at": 4.5,  "type": "type", "text": "/skills", "speed": 100},
    {"at": 6.5,  "type": "key", "key": "Enter"},
    {"at": 8.0,  "type": "wait", "duration": 2.0},
    {"at": 10.0, "type": "subtitle", "text": "56 skills — Chrome DevTools, Firebase, Science, Web, Android"},
    {"at": 12.0, "type": "key", "key": "Down"},
    {"at": 12.3, "type": "key", "key": "Down"},
    {"at": 12.6, "type": "key", "key": "Down"},
    {"at": 12.9, "type": "key", "key": "Down"},
    {"at": 13.2, "type": "key", "key": "Down"},
    {"at": 13.5, "type": "key", "key": "Down"},
    {"at": 13.8, "type": "key", "key": "Down"},
    {"at": 14.1, "type": "key", "key": "Down"},
    {"at": 14.4, "type": "key", "key": "Down"},
    {"at": 14.7, "type": "key", "key": "Down"},
    {"at": 15.0, "type": "key", "key": "Down"},
    {"at": 15.3, "type": "key", "key": "Down"},
    {"at": 16.0, "type": "wait", "duration": 2.0, "subtitle": "Scrolling through Firebase, Science, Modern Web skills"},
    {"at": 19.0, "type": "key", "key": "Escape"},
    {"at": 20.0, "type": "wait", "duration": 1.0},
    {"at": 21.0, "type": "subtitle", "text": "Now let's use a skill to build something"},
    {"at": 22.0, "type": "type", "text": "Use the modern-web-guidance skill to build a responsive card component with CSS container queries. Create the HTML and CSS files.", "speed": 18},
    {"at": 29.0, "type": "key", "key": "Enter"},
    {"at": 30.0, "type": "subtitle", "text": "agy loads the skill, fetches best practices, then generates code"},
    {"at": 30.1, "type": "wait_until_idle", "pattern": "? for shortcuts", "timeout": 120, "poll": 2, "buffer": 5},
    {"at": 31.0, "type": "subtitle", "text": "Skills: domain expertise on demand — ask and agy builds it"},
    {"at": 35.0, "type": "wait", "duration": 1.0}
  ]
}
